{
  "version": "0.4.14-1",
  "sources": {
    "aarch64-darwin": {
      "url": "https://installers.lmstudio.ai/darwin/arm64/0.4.14-1/LM-Studio-0.4.14-1-arm64.dmg",
      "hash": "sha256-YKDG1PZMn16IeFhEPf5lCkLFFnpXi8vzbzbcoJAaoTI="
    },
    "aarch64-linux": {
      "url": "https://installers.lmstudio.ai/linux/arm64/0.4.14-1/LM-Studio-0.4.14-1-arm64.AppImage",
      "hash": "sha256-oAySWxeh+KuUynwIWX/vd0SFoIzuRJioXVCo8EVTG1I="
    },
    "x86_64-linux": {
      "url": "https://installers.lmstudio.ai/linux/x64/0.4.14-1/LM-Studio-0.4.14-1-x64.AppImage",
      "hash": "sha256-Lbq9BAvu2Q4WUlLji6hP01/74H+MCGBeGCV3zl0co4I="
    }
  }
}
